hyperloglog/__init__.py
hyperloglog/const.py
hyperloglog/hll.py
hyperloglog/shll.py
hyperloglog/test/__init__.py
hyperloglog/test/test_hll.py
hyperloglog/test/test_shll.py
hyperloglog-0.1.5.dist-info/LICENSE
hyperloglog-0.1.5.dist-info/METADATA
hyperloglog-0.1.5.dist-info/WHEEL
hyperloglog-0.1.5.dist-info/top_level.txt
hyperloglog-0.1.5.dist-info/RECORD
