Metadata-Version: 2.1
Name: hyperloglog
Version: 0.1.5
Summary: HyperLogLog cardinality counter
Home-page: https://github.com/svpcom/hyperloglog
Author: Vasily Evseenko
Author-email: svpcom@gmail.com
Maintainer: Vasily Evseenko
Maintainer-email: svpcom@gmail.com
License: LGPL 2.1 or later
Requires-Python: >=3.7
License-File: LICENSE
Requires-Dist: msgpack
Requires-Dist: numpy
